gamecam/__init__.py
gamecam/classipy.py
gamecam/pyrcolate.py
gamecam/test/__init__.py
gamecam/test/classipy_test.py
gamecam/test/pyrcolate_test.py
gamecam_sdrabing-0.8.3.data/data/LICENSE.txt
gamecam_sdrabing-0.8.3.dist-info/LICENSE.txt
gamecam_sdrabing-0.8.3.dist-info/METADATA
gamecam_sdrabing-0.8.3.dist-info/WHEEL
gamecam_sdrabing-0.8.3.dist-info/top_level.txt
gamecam_sdrabing-0.8.3.dist-info/RECORD
