Metadata-Version: 2.1
Name: gamecam-sdrabing
Version: 0.8.3
Summary: Remote-camera software suite.
Home-page: https://github.com/shanedrabing/gamecam
Author: Shane Drabing
Author-email: shane.drabing@gmail.com
License: UNKNOWN
Platform: UNKNOWN
Classifier: Programming Language :: Python :: 3
Classifier: License :: OSI Approved :: MIT License
Classifier: Operating System :: OS Independent
Requires-Dist: opencv-python
Requires-Dist: piexif
Requires-Dist: numpy
Requires-Dist: matplotlib
Requires-Dist: scikit-learn
